imhblpce.py
imhblpce-1.0.0.data/scripts/imhblpce
imhblpce-1.0.0.dist-info/LICENSE
imhblpce-1.0.0.dist-info/METADATA
imhblpce-1.0.0.dist-info/WHEEL
imhblpce-1.0.0.dist-info/top_level.txt
imhblpce-1.0.0.dist-info/RECORD
