Metadata-Version: 2.1
Name: imhblpce
Version: 1.0.0
Summary: This module attempts to enhance contrast of a given image by employing a method called HBLPCE.
Home-page: https://github.com/Mamdasn/imhblpce
Author: mamdasn s
Author-email: <mamdassn@gmail.com>
Keywords: python,histogram,imhblpce,hblpce,histogram equalization,histogram based equalization,histogram locality preserving,contrast enhancement
Classifier: Development Status :: 3 - Alpha
Classifier: Intended Audience :: Science/Research
Classifier: License :: OSI Approved :: GNU General Public License v3 (GPLv3)
Classifier: Programming Language :: Python :: 3.8
Classifier: Operating System :: OS Independent
License-File: LICENSE
Requires-Dist: numpy
Requires-Dist: cvxpy
Requires-Dist: numba
Requires-Dist: imhist
